ynd_geosoft_demo/__init__.py
ynd_geosoft_demo/ynd_geosoft_demo.py
ynd_geosoft_demo-0.0.2.dist-info/LICENSE
ynd_geosoft_demo-0.0.2.dist-info/METADATA
ynd_geosoft_demo-0.0.2.dist-info/WHEEL
ynd_geosoft_demo-0.0.2.dist-info/top_level.txt
ynd_geosoft_demo-0.0.2.dist-info/RECORD
