Metadata-Version: 2.1
Name: ynd-geosoft-demo
Version: 0.0.2
Summary: Python package to test my skill on geosoft course
Home-page: https://github.com/YOUNKAP/ynd_geosoft_demo
Author: YOUNKAP NINA Duplex
Author-email: nina.younkap@ccaa.pro
License: MIT license
Keywords: ynd_geosoft_demo
Platform: UNKNOWN
Classifier: Development Status :: 2 - Pre-Alpha
Classifier: Intended Audience :: Developers
Classifier: License :: OSI Approved :: MIT License
Classifier: Natural Language :: English
Classifier: Programming Language :: Python :: 3
Classifier: Programming Language :: Python :: 3.5
Classifier: Programming Language :: Python :: 3.6
Classifier: Programming Language :: Python :: 3.7
Classifier: Programming Language :: Python :: 3.8
Requires-Python: >=3.5
License-File: LICENSE
